main/__init__.py
main/main.py
output/__init__.py
output/stockbit_csv/__init__.py
stockdatadownloader/CommonVariable.py
stockdatadownloader/StockBitColumn.py
stockdatadownloader/__init__.py
stockdatadownloader/fetcher/Idx.py
stockdatadownloader/fetcher/StockBitFetcher.py
stockdatadownloader/fetcher/__init__.py
stockdatadownloader/query/StockBitQuery.py
stockdatadownloader/query/__init__.py
stock_data_downloader_pkg_windoro-0.0.9.dist-info/METADATA
stock_data_downloader_pkg_windoro-0.0.9.dist-info/WHEEL
stock_data_downloader_pkg_windoro-0.0.9.dist-info/top_level.txt
stock_data_downloader_pkg_windoro-0.0.9.dist-info/RECORD
