Metadata-Version: 2.1
Name: stock-data-downloader-pkg-windoro
Version: 0.0.9
Summary: Stock data downloader package
Home-page: https://github.com/windoro/stock-data-downloader
Author: Calvin Windoro
Author-email: calvinwindoro@gmail.com
License: UNKNOWN
Platform: UNKNOWN
Classifier: Programming Language :: Python :: 3
Classifier: License :: OSI Approved :: MIT License
Classifier: Operating System :: OS Independent
Requires-Python: >=3.6
